allscrape/__init__.pyd
allscrape-0.1.4.dist-info/licenses/LICENSE
allscrape-0.1.4.dist-info/METADATA
allscrape-0.1.4.dist-info/WHEEL
allscrape-0.1.4.dist-info/top_level.txt
allscrape-0.1.4.dist-info/zip-safe
allscrape-0.1.4.dist-info/RECORD
